<?xml version="1.0"?>
<mysqldump xmlns:xsi="http://www.w3.org/2001/XMLSchema-instance">
 <database name="">
  <table_structure name="#__fabrik_lists">
   <field Field="id" Type="int" Null="NO" Key="PRI" Extra="auto_increment" />
   <field Field="label" Type="varchar(255)" Null="NO" Key="" Default="" Extra="" />
   <field Field="introduction" Type="text" Null="YES" Key="" Extra="" />
   <field Field="form_id" Type="int" Null="NO" Key="MUL" Default="0" Extra="" />
   <field Field="db_table_name" Type="varchar(255)" Null="NO" Key="" Default="" Extra="" />
   <field Field="db_primary_key" Type="varchar(255)" Null="NO" Key="" Default="" Extra="" />
   <field Field="auto_inc" Type="int" Null="NO" Key="" Default="0" Extra="" />
   <field Field="connection_id" Type="int" Null="NO" Key="" Default="0" Extra="" />
   <field Field="created" Type="datetime" Null="NO" Key="" Extra="" />
   <field Field="created_by" Type="int" Null="NO" Key="" Default="0" Extra="" />
   <field Field="created_by_alias" Type="varchar(255)" Null="NO" Key="" Default="" Extra="" />
   <field Field="modified" Type="datetime" Null="YES" Key="" Extra="" />
   <field Field="modified_by" Type="int" Null="NO" Key="" Default="0" Extra="" />
   <field Field="checked_out" Type="int" Null="NO" Key="" Default="0" Extra="" />
   <field Field="checked_out_time" Type="datetime" Null="YES" Key="" Extra="" />
   <field Field="published" Type="int" Null="NO" Key="" Default="0" Extra="" />
   <field Field="publish_up" Type="datetime" Null="YES" Key="" Extra="" />
   <field Field="publish_down" Type="datetime" Null="YES" Key="" Extra="" />
   <field Field="access" Type="int" Null="NO" Key="" Default="0" Extra="" />
   <field Field="hits" Type="int" Null="NO" Key="" Default="0" Extra="" />
   <field Field="rows_per_page" Type="int" Null="NO" Key="" Default="0" Extra="" />
   <field Field="template" Type="varchar(255)" Null="NO" Key="" Default="" Extra="" />
   <field Field="order_by" Type="varchar(255)" Null="NO" Key="" Default="" Extra="" />
   <field Field="order_dir" Type="varchar(255)" Null="NO" Key="" Default="ASC" Extra="" />
   <field Field="filter_action" Type="varchar(30)" Null="NO" Key="" Default="" Extra="" />
   <field Field="group_by" Type="varchar(255)" Null="NO" Key="" Default="" Extra="" />
   <field Field="private" Type="tinyint(1)" Null="NO" Key="" Default="0" Extra="" />
   <field Field="params" Type="mediumtext" Null="YES" Key="" Extra="" />
   <key Table="#__fabrik_lists" Non_unique="0" Key_name="PRIMARY" Seq_in_index="1" Column_name="id" Collation="A" Null="" Index_type="BTREE" Sub_part="" Comment="" />
   <key Table="#__fabrik_lists" Non_unique="1" Key_name="form_id_INDEX" Seq_in_index="1" Column_name="form_id" Collation="A" Null="" Index_type="BTREE" Sub_part="" Comment="" />
  </table_structure>
 </database>
</mysqldump>