<?xml version="1.0"?>
<mysqldump xmlns:xsi="http://www.w3.org/2001/XMLSchema-instance">
 <database name="">
  <table_structure name="#__emundus_gre">
   <field Field="id" Type="int" Null="NO" Key="PRI" Extra="auto_increment" />
   <field Field="date_time" Type="datetime" Null="YES" Key="" Extra="" />
   <field Field="user" Type="int" Null="YES" Key="MUL" Extra="" />
   <field Field="fnum" Type="varchar(28)" Null="NO" Key="UNI" Extra="" />
   <field Field="Test_Date" Type="datetime" Null="YES" Key="" Extra="" />
   <field Field="Verbal" Type="decimal(8,2)" Null="YES" Key="" Extra="" />
   <field Field="Quantitative" Type="decimal(8,2)" Null="YES" Key="" Extra="" />
   <field Field="Analytical" Type="decimal(8,2)" Null="YES" Key="" Extra="" />
   <field Field="Total" Type="decimal(8,2)" Null="YES" Key="" Extra="" />
   <key Table="#__emundus_gre" Non_unique="0" Key_name="PRIMARY" Seq_in_index="1" Column_name="id" Collation="A" Null="" Index_type="BTREE" Sub_part="" Comment="" />
   <key Table="#__emundus_gre" Non_unique="0" Key_name="fnum" Seq_in_index="1" Column_name="fnum" Collation="A" Null="" Index_type="BTREE" Sub_part="" Comment="" />
   <key Table="#__emundus_gre" Non_unique="1" Key_name="user" Seq_in_index="1" Column_name="user" Collation="A" Null="YES" Index_type="BTREE" Sub_part="" Comment="" />
  </table_structure>
 </database>
</mysqldump>